rnn_classifier/__init__.py
rnn_classifier/model.py
rnn_classifiers-0.0.2.dist-info/LICENSE
rnn_classifiers-0.0.2.dist-info/METADATA
rnn_classifiers-0.0.2.dist-info/WHEEL
rnn_classifiers-0.0.2.dist-info/top_level.txt
rnn_classifiers-0.0.2.dist-info/RECORD
