Metadata-Version: 2.1
Name: rnn-classifiers
Version: 0.0.2
Summary: Pytorch RNN classifiers
Home-page: https://github.com/urchade/Rnn-classifiers
Author: Urchade Zaratiana
Author-email: urchade.zaratiana@gmail.com
License: UNKNOWN
Platform: UNKNOWN
Classifier: Programming Language :: Python :: 3
Classifier: License :: OSI Approved :: MIT License
Classifier: Operating System :: OS Independent
Requires-Python: >=3.6
